action_set_lib/__init__.py
action_set_lib/action_abi.json
action_set_lib/combine.py
action_set_lib/json_reader.py
action_set_lib/actions/__init__.py
action_set_lib/actions/contact/__init__.py
action_set_lib/actions/contact/action_abi.json
action_set_lib/actions/contact/config.json
action_set_lib/actions/contact/contact.py
action_set_lib/actions/transfer/__init__.py
action_set_lib/actions/transfer/action_abi.json
action_set_lib/actions/transfer/config.json
action_set_lib/actions/transfer/transfer.py
action_set_lib/utils/__init__.py
action_set_lib/utils/contact_tool.py
action_set_lib-0.1.1.dist-info/LICENSE
action_set_lib-0.1.1.dist-info/METADATA
action_set_lib-0.1.1.dist-info/WHEEL
action_set_lib-0.1.1.dist-info/top_level.txt
action_set_lib-0.1.1.dist-info/RECORD
